{
  "_id": "ad6c145c-22df-4a83-8621-8596ff3882d0",
  "_outcomes": [
    {
      "displayName": "True",
      "id": "True"
    },
    {
      "displayName": "False",
      "id": "False"
    }
  ],
  "_rev": "689394879",
  "_type": {
    "_id": "ScriptedDecisionNode",
    "collection": true,
    "name": "Scripted Decision",
    "version": "1.0"
  },
  "inputs": [
    "*"
  ],
  "outcomes": [
    "True",
    "False"
  ],
  "outputs": [
    "*"
  ],
  "script": "f1613304-eb87-45a9-8a74-7106074644cb"
}