{
  "_id": "6c6a2fba-ce88-4c25-a2b1-e0bfd9d8b013",
  "_outcomes": [
    {
      "displayName": "true",
      "id": "true"
    },
    {
      "displayName": "false",
      "id": "false"
    }
  ],
  "_rev": "998845985",
  "_type": {
    "_id": "ScriptedDecisionNode",
    "collection": true,
    "name": "Scripted Decision",
    "version": "1.0"
  },
  "inputs": [
    "*"
  ],
  "outcomes": [
    "true",
    "false"
  ],
  "outputs": [
    "*"
  ],
  "script": "b6ed24f8-b63a-4102-bffe-2d0a234fb9eb"
}