[
  {
    "name": "sandbox1",
    "label": "Sandbox1",
    "color": "gray",
    "type": "sandbox"
  },
  {
    "name": "ide3",
    "label": "ide3",
    "color": "green",
    "type": "sandbox"
  },
  {
    "name": "temp-dcc",
    "label": "temp-dcc",
    "color": "blue",
    "type": "controlled",
    "devEnvironment": false
  },
  {
    "name": "ide",
    "label": "IDE",
    "color": "teal",
    "type": "controlled",
    "devEnvironment": true
  },
  {
    "name": "sit",
    "label": "SIT",
    "color": "pink",
    "type": "controlled",
    "devEnvironment": false
  },
  {
    "name": "uat",
    "label": "UAT",
    "color": "purple",
    "type": "controlled",
    "devEnvironment": false
  }
]