{
  "_id": "64c9c15e-df0c-4850-a2a2-e000be85e80e",
  "_outcomes": [
    {
      "displayName": "true",
      "id": "true"
    },
    {
      "displayName": "false",
      "id": "false"
    }
  ],
  "_rev": "1238696167",
  "_type": {
    "_id": "ScriptedDecisionNode",
    "collection": true,
    "name": "Scripted Decision",
    "version": "1.0"
  },
  "inputs": [
    "*"
  ],
  "outcomes": [
    "true",
    "false"
  ],
  "outputs": [
    "*"
  ],
  "script": "6e9b52ae-47b4-41c3-9813-37875bfcb4e9"
}