{
  "_id": "58924af6-23f3-4ee1-9f29-30d38252c713",
  "_outcomes": [
    {
      "displayName": "True",
      "id": "true"
    },
    {
      "displayName": "False",
      "id": "false"
    }
  ],
  "_rev": "1577774114",
  "_type": {
    "_id": "PageNode",
    "collection": true,
    "name": "Page Node",
    "version": "1.0"
  },
  "nodes": [
    {
      "_id": "0a10b03e-c07f-4b3d-abf8-910ade92c204",
      "displayName": "Message Node",
      "nodeType": "MessageNode",
      "nodeVersion": "1.0"
    }
  ],
  "pageDescription": {},
  "pageHeader": {}
}