{
  "_id": "emailTemplate/kyidResetPassword",
  "advancedEditor": true,
  "defaultLocale": "en",
  "description": "",
  "displayName": "kyidResetPassword",
  "enabled": true,
  "from": "",
  "html": {
    "en": {
      "file": "kyidResetPassword.en.html"
    }
  },
  "message": {
    "en": {
      "file": "kyidResetPassword.en.md"
    }
  },
  "mimeType": "text/html",
  "styles": {
    "file": "kyidResetPassword.css"
  },
  "subject": {
    "en": "KYID Account Password Reset Successful"
  },
  "templateId": "kyidResetPassword"
}