{
  "_id": "490914ae-6af2-4faf-bfd6-a7edeeae00fa",
  "context": "CONFIG_PROVIDER_NODE",
  "createdBy": "id=4457bbed-e100-419a-b946-76121d9779e6,ou=user,ou=am-config",
  "creationDate": 1731536946865,
  "default": false,
  "description": "null",
  "evaluatorVersion": "1.0",
  "language": "JAVASCRIPT",
  "lastModifiedBy": "id=59467349-22e0-4423-bbf8-fd1cec770795,ou=user,ou=am-config",
  "lastModifiedDate": 1737555796136,
  "name": "KYID.Journey.cLocaleCookieENSet",
  "script": {
    "file": "scripts-content/CONFIG_PROVIDER_NODE/KYID.Journey.cLocaleCookieENSet.js"
  }
}