{
  "_id": "6d739c18-4c69-4ce3-9847-16b2fe92c01f",
  "context": "AUTHENTICATION_TREE_DECISION_NODE",
  "createdBy": "id=4457bbed-e100-419a-b946-76121d9779e6,ou=user,ou=am-config",
  "creationDate": 1731536949199,
  "default": false,
  "description": "This script is used to route to login main journey.",
  "evaluatorVersion": "2.0",
  "language": "JAVASCRIPT",
  "lastModifiedBy": "id=4457bbed-e100-419a-b946-76121d9779e6,ou=user,ou=am-config",
  "lastModifiedDate": 1731546263061,
  "name": "KYID.Journey.loginMainRouterJourney",
  "script": {
    "file": "scripts-content/AUTHENTICATION_TREE_DECISION_NODE/KYID.Journey.loginMainRouterJourney.js"
  }
}