{
  "_id": "a854de0d-e8df-49a2-a311-081adf4f158e",
  "context": "AUTHENTICATION_TREE_DECISION_NODE",
  "createdBy": "id=52b0c7a6-4d39-47a3-af74-bd210d8af08c,ou=user,ou=am-config",
  "creationDate": 1740995089772,
  "default": false,
  "description": "This script is used to obtain list of prerequisites.",
  "evaluatorVersion": "2.0",
  "language": "JAVASCRIPT",
  "lastModifiedBy": "id=6577c553-c881-4432-8ae6-1892c782b952,ou=user,ou=am-config",
  "lastModifiedDate": 1742797002593,
  "name": "KYID.Journey.GetListOfPreRequisites",
  "script": {
    "file": "scripts-content/AUTHENTICATION_TREE_DECISION_NODE/KYID.Journey.GetListOfPreRequisites.js"
  }
}