{
  "application": {
    "_rev": "bd3e26a0-6dd0-4e0e-acc9-7ab5e91f03ad-424365",
    "description": "SEBT",
    "fr": {
      "realm": "alpha"
    },
    "id": "eccf44fe-d061-421e-af6f-d9ba4d9b00cb",
    "metadata": {
      "entityType": "/openidm/managed/application",
      "created": "2025-05-19T06:41:17.223Z"
    },
    "name": "SEBT",
    "url": "www.SEBT.com"
  },
  "id": "eccf44fe-d061-421e-af6f-d9ba4d9b00cb",
  "item": {
    "type": "accountGrant"
  },
  "latestModified": {
    "application": "2025-05-19T06:41:17.223Z"
  },
  "metadata": {
    "modifiedDate": "2025-05-19T06:45:10.63767797Z",
    "createdDate": "2025-05-19T06:45:10.63767797Z"
  },
  "permissions": {
    "createEntitlement": true
  }
}