{
  "_id": "2a65698a-4398-42b5-a4e6-8a4aa39ae656",
  "_outcomes": [
    {
      "displayName": "Confirm",
      "id": "Confirm"
    },
    {
      "displayName": "GoBack",
      "id": "GoBack"
    }
  ],
  "_rev": "-1888521795",
  "_type": {
    "_id": "ScriptedDecisionNode",
    "collection": true,
    "name": "Scripted Decision",
    "version": "1.0"
  },
  "inputs": [
    "*"
  ],
  "outcomes": [
    "Confirm",
    "GoBack"
  ],
  "outputs": [
    "*"
  ],
  "script": "c40f3b8e-0eb0-4e88-a5d1-723447b76311"
}