{
  "_id": "3c7c7753-56d0-472f-a19a-8937a33ab856",
  "context": "AUTHENTICATION_TREE_DECISION_NODE",
  "createdBy": "null",
  "creationDate": 0,
  "default": false,
  "description": "This journey script displays the success message of MFA registration.",
  "evaluatorVersion": "2.0",
  "language": "JAVASCRIPT",
  "lastModifiedBy": "id=95ef9650-e4b7-4a95-ac95-49b66b061073,ou=user,ou=am-config",
  "lastModifiedDate": 1754287830247,
  "name": "kyid.journey.registration.mfa.success",
  "script": {
    "file": "scripts-content/AUTHENTICATION_TREE_DECISION_NODE/kyid.journey.registration.mfa.success.js"
  }
}