{
  "_id": "4867617d-f4e5-4034-84b0-5626f7659a79",
  "context": "CONFIG_PROVIDER_NODE",
  "createdBy": "id=95ef9650-e4b7-4a95-ac95-49b66b061073,ou=user,ou=am-config",
  "creationDate": 1754286695276,
  "default": false,
  "description": "null",
  "evaluatorVersion": "1.0",
  "language": "JAVASCRIPT",
  "lastModifiedBy": "id=95ef9650-e4b7-4a95-ac95-49b66b061073,ou=user,ou=am-config",
  "lastModifiedDate": 1755485422718,
  "name": "KYID.2B1.Journey.RedirectToRequestAccess",
  "script": {
    "file": "scripts-content/CONFIG_PROVIDER_NODE/KYID.2B1.Journey.RedirectToRequestAccess.js"
  }
}