{
  "_id": "d6981b8e-83b6-4d8a-a83c-e2b1e8824144",
  "_outcomes": [
    {
      "displayName": "True",
      "id": "True"
    },
    {
      "displayName": "False",
      "id": "False"
    }
  ],
  "_rev": "1390290858",
  "_type": {
    "_id": "ScriptedDecisionNode",
    "collection": true,
    "name": "Scripted Decision",
    "version": "1.0"
  },
  "inputs": [
    "*"
  ],
  "outcomes": [
    "True",
    "False"
  ],
  "outputs": [
    "*"
  ],
  "script": "e4508d8d-1796-4610-b00f-9b62308be4e9"
}