{
  "_id": "79d922f0-880d-4e56-a496-30f9250a9cad",
  "_outcomes": [
    {
      "displayName": "KBABack",
      "id": "KBABack"
    },
    {
      "displayName": "anotherMethod",
      "id": "anotherMethod"
    },
    {
      "displayName": "Next",
      "id": "Next"
    },
    {
      "displayName": "FARS",
      "id": "FARS"
    }
  ],
  "_rev": "-1630166406",
  "_type": {
    "_id": "ScriptedDecisionNode",
    "collection": true,
    "name": "Scripted Decision",
    "version": "1.0"
  },
  "inputs": [
    "*"
  ],
  "outcomes": [
    "KBABack",
    "anotherMethod",
    "Next",
    "FARS"
  ],
  "outputs": [
    "*"
  ],
  "script": "fc2c71b3-0b49-4bc0-bb3b-3170011c921f"
}