{
  "_id": "472f5257-49de-4e95-ac68-52c292b2a907",
  "_outcomes": [
    {
      "displayName": "true",
      "id": "true"
    },
    {
      "displayName": "false",
      "id": "false"
    }
  ],
  "_rev": "1991855798",
  "_type": {
    "_id": "ScriptedDecisionNode",
    "collection": true,
    "name": "Scripted Decision",
    "version": "1.0"
  },
  "inputs": [
    "*"
  ],
  "outcomes": [
    "true",
    "false"
  ],
  "outputs": [
    "*"
  ],
  "script": "c9a626f8-3777-48ab-8ae7-67c53a8da3c9"
}