{
  "_id": "608afe6f-df13-45f8-9ceb-61db47d72b46",
  "_outcomes": [
    {
      "displayName": "true",
      "id": "true"
    },
    {
      "displayName": "false",
      "id": "false"
    }
  ],
  "_rev": "-1382636497",
  "_type": {
    "_id": "ScriptedDecisionNode",
    "collection": true,
    "name": "Scripted Decision",
    "version": "1.0"
  },
  "inputs": [
    "*"
  ],
  "outcomes": [
    "true",
    "false"
  ],
  "outputs": [
    "*"
  ],
  "script": "40853afa-5874-49f0-b8f7-c02d3feebd7f"
}