{
  "_id": "1eef14ad-ba9c-48b9-97b5-0c74ff46dfcf",
  "_outcomes": [
    {
      "displayName": "true",
      "id": "true"
    },
    {
      "displayName": "false",
      "id": "false"
    }
  ],
  "_rev": "-285098174",
  "_type": {
    "_id": "ScriptedDecisionNode",
    "collection": true,
    "name": "Scripted Decision",
    "version": "1.0"
  },
  "inputs": [
    "*"
  ],
  "outcomes": [
    "true",
    "false"
  ],
  "outputs": [
    "*"
  ],
  "script": "0e221803-a9d2-47c7-a366-625175c8332c"
}