{
  "_id": "3e658679-cf52-4be7-8535-43697a6a9103",
  "context": "AUTHENTICATION_TREE_DECISION_NODE",
  "createdBy": "id=53efca5d-5f18-4189-9665-f87004ef8555,ou=user,ou=am-config",
  "creationDate": 1747320018425,
  "default": false,
  "description": "This script is used to read device context from login request.",
  "evaluatorVersion": "2.0",
  "language": "JAVASCRIPT",
  "lastModifiedBy": "id=53efca5d-5f18-4189-9665-f87004ef8555,ou=user,ou=am-config",
  "lastModifiedDate": 1765950799009,
  "name": "KYID.Journey.ReadDeviceInformation",
  "script": {
    "file": "scripts-content/AUTHENTICATION_TREE_DECISION_NODE/KYID.Journey.ReadDeviceInformation.js"
  }
}