{
  "_id": "66eecc33-f281-4f67-b399-722f8e350356",
  "_outcomes": [
    {
      "displayName": "Confirm",
      "id": "Confirm"
    },
    {
      "displayName": "GoBack",
      "id": "GoBack"
    }
  ],
  "_rev": "-1712867916",
  "_type": {
    "_id": "ScriptedDecisionNode",
    "collection": true,
    "name": "Scripted Decision",
    "version": "1.0"
  },
  "inputs": [
    "*"
  ],
  "outcomes": [
    "Confirm",
    "GoBack"
  ],
  "outputs": [
    "*"
  ],
  "script": "cfd58417-66c2-4727-8423-3ea5d9e0522c"
}