{
  "_id": "f57ef3aa-5444-4759-9390-85896c199182",
  "context": "AUTHENTICATION_TREE_DECISION_NODE",
  "createdBy": "id=95ef9650-e4b7-4a95-ac95-49b66b061073,ou=user,ou=am-config",
  "creationDate": 1754286701721,
  "default": false,
  "description": "This script is used to add or remove mobile number in KOG using SIH API.",
  "evaluatorVersion": "2.0",
  "language": "JAVASCRIPT",
  "lastModifiedBy": "id=95ef9650-e4b7-4a95-ac95-49b66b061073,ou=user,ou=am-config",
  "lastModifiedDate": 1773208557037,
  "name": "KYID.2B1.Journey.AddRemoveMobilePhoneSIHAPI",
  "script": {
    "file": "scripts-content/AUTHENTICATION_TREE_DECISION_NODE/KYID.2B1.Journey.AddRemoveMobilePhoneSIHAPI.js"
  }
}